{"拼音": "huà", "部首": "田", "笔画数": "8", "Unicode": "753B", "page": "759", "volume": "【午集上】【田字部】", "notes": "\r\n\r\n【字彙】胡卦切，與畫同。繪也。\n\r\n（畫）〔古文〕𤱪𨽶𤲯。【唐韻】【集韻】【韻會】【正韻】𠀤胡麥切，橫入聲。卦畫也。　又分畫也。界限也。【左傳·襄四年】芒芒禹迹，畫爲九州。【註】畫分也。【禮·檀弓】哀公使人弔蕢尚，遇諸道，辟於路，畫宮而受弔焉。【註】畫地爲宮象。　又計策也。【鄒陽·上吳王書】故願大王審畫而已。【史記·荆燕世家】齊人田生游，乏資，以畫干營陵侯澤。【註】服䖍曰：以計畫干之也。　又截止也。【論語】今女畫。　又丘名。【爾雅·釋地】途出其右，而還之畫丘。【註】言爲道所規畫。【釋名】道出其右曰畫。丘人尚右，凡有指畫，皆用右也。　又地名。【史記·田單傳】燕之初入齊，聞畫邑人王蠋賢。【註】正義曰：括地志云：戟里城在臨湽西北三十里，春秋時棘邑。又云澅邑，蠋所居卽此邑，因澅水爲名也。　\n\r\n又【廣韻】【集韻】【韻會】【正韻】𠀤胡卦切，音話。【爾雅·釋言】畫形也。【註】畫者爲形像。【釋名】畫，挂也。以五色挂物象也。俗作𦘕。【周禮·天官·典絲】凡祭祀共黼畫組就之物。【疏】凡祭服皆畫衣繡裳。【儀禮·鄕射禮】大夫布侯，畫以虎豹。士布侯，畫以鹿豕。　又官名。【後漢·百官志】畫室署長一人，四百石，黃綬。　\n\r\n又【韻補】叶胡對切，音惠。【秦瑯琊刻石】方伯分職，諸治經易。舉錯必當，莫不如畫。易音異。"}