{"拼音": "jiāng,jiàng,qiáng", "部首": "田", "笔画数": "19", "Unicode": "7586", "page": "766", "volume": "【午集上】【田字部】", "notes": "\r\n\r\n【唐韻】【集韻】【韻會】【正韻】𠀤居良切，音薑。【說文】本作畺，界也。【易·坤卦】坤厚載物，德合无疆。【書·泰誓】我武惟揚，侵于之疆。【詩·小雅】萬壽無疆。【箋】疆，竟界也。【左傳·桓十七年】夏，及齊師戰於奚，疆事也。【註】爭疆界也。　\n\r\n又【詩·大雅】迺疆迺理。【朱註】疆謂畫其大界。【左傳·宣八年】楚伐舒蓼滅之，楚子疆之。【註】正其界也。　又官名。【周禮·夏官】掌疆。【疏】掌守疆界，亦是禁戒之事。　\n\r\n又【集韻】或作彊。【賈誼·新書】衞侯名辟彊。辟彊，天子之事也。諸侯弗得用，衞侯更名燬。　又或作壃。【史記·晉世家】出壃乃免。　\n\r\n又【正韻】蠶白也。　\n\r\n又【集韻】【正韻】𠀤巨兩切，强上聲。【周禮·地官·草人】疆㯺用蕡。【註】疆㯺，疆堅者。【釋文】疆，其兩反。　\n\r\n又【字彙補】北方謂土焦曰疆。見轉注古音。"}