{"拼音": "chāo,miǎo", "部首": "言", "笔画数": "11", "Unicode": "8A2C", "page": "1151", "volume": "【酉集上】【言字部】", "notes": "\r\n\r\n【唐韻】楚交切【集韻】初交切，𠀤音抄。【說文】訬，擾也。一曰訬儈。　\n\r\n又【玉篇】健也，疾也。【淮南子·修務訓】越人有重遲者，而人謂之訬。【註】訬，輕利善趨者。　又訬婧，細腰貌。【後漢·張衡傳·思𤣥賦】舒訬婧之纖腰。【文選註】亦音眇。　\n\r\n又【類篇】書也。　又人名。𨻰訬，見【梁書】。　\n\r\n又【集韻】鋤交切，音巢。【博雅】獪也。　\n\r\n又【廣韻】亡沼切【集韻】弭沼切，𠀤音眇。【說文】義同。　\n\r\n又【類篇】高也。【張衡·西京賦】通天訬以竦峙。【註】通天，臺名。訬，高也。李善讀。　\n\r\n又【集韻】七肖切，音峭。輕也，江東語。　\n\r\n又【集韻】楚敎切，抄去聲。義同。【前漢·班固敘傳】江都訬輕。【註】訬，謂輕狡也。師古讀。【集韻】或作吵。　\n\r\n又【集韻】楚絞切，抄上聲。與謅同。【集韻】七肖切。七省切，誤。\n\r\n考證：〔【集韻】七省切，音峭。輕也，江東語。〕　謹照原文七省切改七肖切。"}