{"拼音": "bó", "部首": "馬", "笔画数": "16", "Unicode": "99EE", "page": "1438", "volume": "【亥集上】【馬字部】", "notes": "\r\n\r\n【唐韻】【集韻】【韻會】北角切，𠀤音剝。【山海經】中曲山有獸，如馬而身黑，二尾一角，虎牙爪，音如鼓，名曰駮，食虎豹，可以禦兵。【正字通】此獸之別一種，非馬族也。【詩·秦風】隰有六駮。【傳】駮如馬。【疏】陸機云：駮馬，梓楡也。其樹皮靑白駮犖，遙視似駮馬，故謂之駮馬。下章云：山有苞棣，隰有樹檖，皆山隰之木相配，不宜云獸。　又國名。四裔駮馬地近北海，唐永𡽪中，遣使朝賀。　又秦叔寶有乗馬名忽雷駮。　又朝廷章奏不合事理，別議改正曰駮。【前漢·𠛬法志】文書盈於几閣，典者不能遍睹，是以郡國承用者駮。【註】不曉其指，用意不同也。【王球貽謀錄】給事中掌封駮司，不可一日無。淳化四年，太宗推考，廢職始於唐末，乃命魏庠柴成務，同知給事中。未幾，隷銀臺通進司，爲封駮司。眞宗咸平四年，吏部侍郞知封駮事，陳恕乞鑄印，命取門下印用之，因改名爲門下封駮司。　\n\r\n又【正字通】論列是非，亦謂之駮。如柳宗元駮復讎議，夏侯銛駮安定公主合葬議，是也。○按駮與駁同，《九經字樣》泥《說文》，分駁、駮爲二者，非。\n\r\n考證：〔【詩·秦風】隰有六駮。【傳】駮〈如下馬〉。〕　謹照〈如下馬〉乃如馬二字之譌。謹照原文駮〈如下馬〉改爲駮如馬。"}